Samco_modular/__init__.py
Samco_modular/auto_sqoff.py
Samco_modular/buyside_sqoff.py
Samco_modular/create_log.py
Samco_modular/df_strike_gen.py
Samco_modular/inputs.py
Samco_modular/logging_funcs.py
Samco_modular/login.py
Samco_modular/order_place.py
Samco_modular/pip_installs.py
Samco_modular/scripmaster_download.py
Samco_modular/sl_monitoring.py
Samco_modular/stoploss_place.py
Samco_modular-0.0.30.dist-info/LICENCE.txt
Samco_modular-0.0.30.dist-info/METADATA
Samco_modular-0.0.30.dist-info/WHEEL
Samco_modular-0.0.30.dist-info/top_level.txt
Samco_modular-0.0.30.dist-info/RECORD
