Metadata-Version: 2.1
Name: Samco_modular
Version: 0.0.30
Summary: For generating df_strike_price dataframe
Home-page: https://pypi.org/project/Samco-modular/0.0.26/
Author: Denny Babu
Author-email: dannibabup@gmail.com
Classifier: Programming Language :: Python :: 3
Classifier: License :: OSI Approved :: MIT License
Classifier: Operating System :: OS Independent
Requires-Python: >=3.7
License-File: LICENCE.txt
